supercode/__init__.py
supercode/core.py
supercode-2.2.3.dist-info/METADATA
supercode-2.2.3.dist-info/WHEEL
supercode-2.2.3.dist-info/entry_points.txt
supercode-2.2.3.dist-info/top_level.txt
supercode-2.2.3.dist-info/RECORD
